PyCoupang/__init__.py
PyCoupang/api.py
PyCoupang/config/__init__.py
PyCoupang/config/info.py
PyCoupang-0.0.1.dist-info/METADATA
PyCoupang-0.0.1.dist-info/WHEEL
PyCoupang-0.0.1.dist-info/top_level.txt
PyCoupang-0.0.1.dist-info/RECORD
