Metadata-Version: 2.1
Name: PyCoupang
Version: 0.0.1
Summary: Coupang Open API Python Wrapper
Home-page: https://github.com/WooilJeong/PyCoupang
Author: 정우일(Wooil Jeong)
Author-email: wooil@kakao.com
License: MIT
Platform: UNKNOWN
Classifier: Programming Language :: Python :: 3
Classifier: License :: OSI Approved :: MIT License
Classifier: Operating System :: OS Independent
